<?xml version="1.0" encoding="UTF-8"?>
<TRANSFER xmlns="http://www.interlis.ch/INTERLIS2.3">
    <HEADERSECTION SENDER="mkilimodelsxml-1.6.3-20120220" VERSION="2.3">
        <MODELS>
            <MODEL NAME="IliRepository10" VERSION="2017-08-10" URI="mailto:agenciadeimplementacion@incige.com"/>
        </MODELS>
    </HEADERSECTION>
    <DATASECTION>
        <IliRepository10.RepositoryIndex BID="b1">
            
            <IliRepository10.RepositoryIndex.ModelMetadata TID="42">
                <Name>IliVErrors</Name>
                <SchemaLanguage>ili2_3</SchemaLanguage>
                <File>tools/IliVErrors.ili</File>
                <Version>2016-06-10</Version>
                <publishingDate>2017-01-12</publishingDate>
                <Issuer>mailto:ceis@localhost</Issuer>
                <md5>b41ab92753368ad32890d04bc77cc47f</md5>
            </IliRepository10.RepositoryIndex.ModelMetadata>

            <!--IliRepository10.RepositoryIndex.ModelMetadata TID="45">
                <Name>CoordSys</Name>
                <SchemaLanguage>ili2_2</SchemaLanguage>
                <File>refhb22/CoordSys-20151123.ili</File>
                <Version>2015-11-23</Version>
                <publishingDate>2017-04-10</publishingDate>
                <precursorVersion>2003-03-18</precursorVersion>
                <md5>5e12919a0dff1fb23dd0d92a4873748d</md5>
            </IliRepository10.RepositoryIndex.ModelMetadata>

            <IliRepository10.RepositoryIndex.ModelMetadata TID="46">
                <Name>StandardSymbology</Name>
                <SchemaLanguage>ili2_2</SchemaLanguage>
                <File>refhb22/StandardSymbology-20160120.ili</File>
                <Version>2016-01-20</Version>
                <publishingDate>2017-04-10</publishingDate>
                <dependsOnModel>
                    <IliRepository10.ModelName_>
                        <value>AbstractSymbology</value>
                    </IliRepository10.ModelName_>
                </dependsOnModel>
                <precursorVersion>2015-04-01</precursorVersion>
                <md5>34f535881a0d89639be4d4db656ef929</md5>
            </IliRepository10.RepositoryIndex.ModelMetadata>

            <IliRepository10.RepositoryIndex.ModelMetadata TID="47">
                <Name>Units</Name>
                <SchemaLanguage>ili2_2</SchemaLanguage>
                <File>refhb22/Units-20120219.ili</File>
                <Version>2012-02-19</Version>
                <publishingDate>2017-04-10</publishingDate>
                <precursorVersion>2003-03-18</precursorVersion>
                <md5>ce2f5833386b6b8b5acceef87f0b492a</md5>
            </IliRepository10.RepositoryIndex.ModelMetadata>

            <IliRepository10.RepositoryIndex.ModelMetadata TID="48">
                <Name>Time</Name>
                <SchemaLanguage>ili2_2</SchemaLanguage>
                <File>refhb22/Time-20170412.ili</File>
                <Version>2017-04-12</Version>
                <publishingDate>2017-04-13</publishingDate>
                <dependsOnModel>
                    <IliRepository10.ModelName_>
                        <value>Units</value>
                    </IliRepository10.ModelName_>
                </dependsOnModel>
                <precursorVersion>2003-03-18</precursorVersion>
                <md5>196c9799ac39d9f05d95e96cbdf0e481</md5>
            </IliRepository10.RepositoryIndex.ModelMetadata>

            <IliRepository10.RepositoryIndex.ModelMetadata TID="49">
                <Name>Time</Name>
                <SchemaLanguage>ili2_3</SchemaLanguage>
                <File>refhb23/Time-20170413.ili</File>
                <Version>2017-04-13</Version>
                <publishingDate>2017-04-13</publishingDate>
                <dependsOnModel>
                    <IliRepository10.ModelName_>
                        <value>Units</value>
                    </IliRepository10.ModelName_>
                </dependsOnModel>
                <precursorVersion>2005-06-16</precursorVersion>
                <md5>26ed79dec1e50e4326707930ef39adf3</md5>
            </IliRepository10.RepositoryIndex.ModelMetadata-->

        </IliRepository10.RepositoryIndex>
    </DATASECTION>
</TRANSFER>
